Workbook

Sheet Sheet1
A1: 细分板块 | B1: 代码 | C1: 公司名称 | D1: 06/07前复权最高点至07月最低点跌幅(%) | E1: 上周收盘价(2026-07-31) | F1: 今日收盘价(2026-08-07) | G1: 涨跌额(元) | H1: 阶段涨幅(%) | I1: 数据状态 | J1: 备注
A2: InP衬底 | B2: 002428 | C2: 云南锗业 | D2: =ROUND((Data!C2-Data!E2)/Data!C2*100,2) -> 54.24 | E2: 66.95 | F2: 100.08 | G2: 33.13 | H2: 49.48 | I2: 正常 | J2: 云南鑫耀磷化铟衬底已批量供货，2025年产能15万片/年、2026年规划18万片并启动扩产；AI光模块上游映射直接，风险是客户/订单金额、良率、6英寸量产和利润贡献仍披露不足。证据A/B。
A3: 高纯湿电子化学品 | B3: 688549 | C3: 中巨芯-U | D3: =ROUND((Data!C3-Data!E3)/Data!C3*100,2) -> 57.95 | E3: 19.53 | F3: 28.77 | G3: 9.24 | H3: 47.31 | I3: 正常 | J3: 证据中：2025年报显示公司同时覆盖电子湿化学品、电子特种气体和前驱体材料，其中电子湿化学品收入占比约72.5%，电子特气及前驱体占比约23.9%；公司仍亏损，故由ALD-CVD前驱体修正为电子湿化学品。
A4: AI服务器高速PCB | B4: 300476 | C4: 胜宏科技 | D4: =ROUND((Data!C4-Data!E4)/Data!C4*100,2) -> 53.4 | E4: 190.4 | F4: 280.2 | G4: 89.8 | H4: 47.16 | I4: 正常 | J4: 高多层PCB、HDI和AI服务器/交换机PCB是最直接主线，年报披露AI服务器相关HDI及18层以上多层板高景气，并强调深度绑定国际头部客户；主板块保留AI服务器高速PCB，风险是大客户集中、扩产良率和海外交付节奏。证据A/B。2026-06-16 JPM补充：报告从AI switch、midplane/HDI和高层PCB良率角度强化AI PCB价值量与制造难度，支持胜宏高层高速板需求侧；风险仍是扩产良率、客户集中和毛利年降。
A5: 光芯片 | B5: 688313 | C5: 仕佳光子 | D5: =ROUND((Data!C5-Data!E5)/Data!C5*100,2) -> 60.48 | E5: 90.04 | F5: 127.7 | G5: 37.66 | H5: 41.83 | I5: 正常 | J5: 具备AWG/PLC无源芯片、DFB/CW DFB与EML研发能力，CW DFB已小批量交付、EML仍在验证；主板块保留光芯片，但偏无源+有源平台，业绩弹性取决于1.6T/CPO客户导入。证据B。
A6: 载体铜箔 | B6: 688020 | C6: 方邦股份 | D6: =ROUND((Data!C6-Data!E6)/Data!C6*100,2) -> 67.93 | E6: 103.27 | F6: 146.16 | G6: 42.89 | H6: 41.53 | I6: 正常 | J6: 可剥离超薄载体铜箔面向IC载板/先进封装，部分规格通过载板厂和终端客户认证并持续小批量订单；主板块由高端铜箔改为载体铜箔，EMI屏蔽降级为非AI主线，不再单列，风险是规模收入和盈利兑现仍小。证据B。
A7: 高端封装填料 | B7: 688300 | C7: 联瑞新材 | D7: =ROUND((Data!C7-Data!E7)/Data!C7*100,2) -> 65.25 | E7: 107.32 | F7: 151.7 | G7: 44.38 | H7: 41.35 | I7: 正常 | J7: 功能性粉体材料龙头，年报披露聚焦AI/5G/HPC高端芯片封装、Chiplet/HBM异构集成和M8/M9/M10高速覆铜板，Low-alpha球硅/球铝及低损耗球硅是先进封装和高速基板关键填料。主板块保留高端封装填料，封装基板材料并入备注，风险是客户认证、价格竞争和高端新品占比。证据A。
A8: TFLN | B8: 300620 | C8: 光库科技 | D8: =ROUND((Data!C8-Data!E8)/Data!C8*100,2) -> 55.4 | E8: 205.3 | F8: 288.08 | G8: 82.78 | H8: 40.32 | I8: 正常 | J8: 光通信器件是当前业绩主线：2026H1归母预告1.40–1.50亿元、同比+170%–190%（未经审计；Q1增长含武汉光库并表）。TFLN为高端调制器路线：骨干网CDM芯片已批量出货、模块小批量；DCI及数据中心/AI集群PAM4仍验证送样且进度延后，不能按800G/1.6T量产收入计。安捷讯拟收购补高速模块组件及机房光互联，MT/FAU/MPO类存在产品重叠；截至2026-07-31深交所项目状态为“已问询”，交割后方能并表，若2026H2交割，完整年度贡献最早看2027。主板块保留TFLN，风险是验证转量产、项目效益/利用率、审批交割及数通产品降价。证据A（截至2026-07-31）。
A9: 高端高速铜箔 | B9: 301217 | C9: 铜冠铜箔 | D9: =ROUND((Data!C9-Data!E9)/Data!C9*100,2) -> 61.77 | E9: 82.62 | F9: 115.81 | G9: 33.19 | H9: 40.17 | I9: 正常 | J9: 2026H1业绩预告：预计归母净利润2.05—2.25亿元（同比+486.49%—543.70%），扣非净利润2.00—2.20亿元（同比+724.05%—806.45%）；公司明确称聚焦头部客户需求，高频高速铜箔供不应求、销量同比增长，高附加值产品占比与加工费收入提升，降本带动毛利率改善，支持AI PCB材料景气已通过销量、结构和加工费进入利润表。仍未拆分HVLP代际、AI客户/收入占比及单吨加工费，且高频高速铜箔不等同全部AI收入；继续跟踪半年报分产品毛利和经营现金流。证据A。
A10: PCB湿化学 | B10: 688603 | C10: 天承科技 | D10: =ROUND((Data!C10-Data!E10)/Data!C10*100,2) -> 62.63 | E10: 83.73 | F10: 117.3 | G10: 33.57 | H10: 40.09 | I10: 正常 | J10: PCB专用电子化学品公司，产品覆盖沉铜、电镀、表面处理和棕化等湿制程，高层高密AI PCB、mSAP和封装基板升级提高药水纯度和工艺门槛；主板块保留PCB湿化学，风险是客户扩产周期、原料价格和海外市场验证。证据A。
A11: 薄膜滤波片 | B11: 688195 | C11: 腾景科技 | D11: =ROUND((Data!C11-Data!E11)/Data!C11*100,2) -> 60.84 | E11: 108.05 | F11: 150.14 | G11: 42.09 | H11: 38.95 | I11: 正常 | J11: 精密光学和光纤器件平台，2025半年报披露数据中心CWDM滤光片可规模化低成本供应，并具备WSS关键球柱面镜、微透镜等能力；主板块改为薄膜滤波片，法拉第旋光片、OCS光交换和微透镜并入备注降级为相邻精密光学能力，风险是AI数据中心客户订单和收入占比披露不足。证据B。
A12: 高端高速CCL | B12: 688519 | C12: 南亚新材 | D12: =ROUND((Data!C12-Data!E12)/Data!C12*100,2) -> 56.35 | E12: 218 | F12: 302.55 | G12: 84.55 | H12: 38.78 | I12: 正常 | J12: 高频高速覆铜板主线，AI服务器/光模块用高速板材料明确，M8/M9/M10升级看客户认证、订单能见度和涨价传导；封装基板材料并入备注，不再单列主板块。证据B。2026-06-16 JPM补充：报告提示HPC CCL/PCB TAM由AI server、常规server、LEO共同推升，CCL TAM可按2.5-3倍近似外推PCB TAM，M9升级和载板用Q glass是新增验证方向；仍按B级卖方估算处理，需看分产品lead time、涨价、客户认证和收入毛利。
A13: TFLN | B13: 600330 | C13: 天通股份 | D13: =ROUND((Data!C13-Data!E13)/Data!C13*100,2) -> 58.04 | E13: 16.61 | F13: 23.01 | G13: 6.4 | H13: 38.53 | I13: 正常 | J13: 铌酸锂晶体、晶片和材料端平台，薄膜铌酸锂/TFLN属于高速调制器上游材料观察；公司更接近TFLN材料端而非器件或光模块，业绩弹性取决于薄膜铌酸锂晶片量产客户和收入占比。主板块保留TFLN，风险是材料验证周期、需求放量节奏和传统磁材/蓝宝石周期。证据B/C。
... A375: AI眼镜主控SoC | B375: 688608 | C375: 恒玄科技 | D375: =ROUND((Data!C375-Data!E375)/Data!C375*100,2) -> 21.13 | E375: 123.87 | F375: 112.31 | G375: -11.56 | H375: -9.33 | I375: 正常 | J375: 证据强：2025年报披露公司主营低功耗无线计算SoC，芯片集成CPU、嵌入式NPU、ISP、DSP、蓝牙/Wi-Fi等模块；BES6100面向智能眼镜等低功耗终端，6nm工艺，集成多核Cortex-A、NPU、GPU，可运行Linux/Android并支持端侧AI推理。风险是AI眼镜SoC仍处放量早期，需跟踪客户导入和量产节奏。
A376: 半导体测试服务 | B376: 430139 | C376: 华岭股份 | I376: 未找到通达信日线文件 | J376: 证据中：2025年报显示测试服务仍为核心收入来源，并建设高算力应用芯片开放式测试创新服务平台；但公司2025年亏损扩大，AI/高算力测试仍处研发和客户拓展阶段，主线保留半导体测试服务，备注降级AI兑现强度。

Sheet Data
A1: 代码 | B1: 最高点日期 | C1: 06/07前复权最高日内价 | D1: 最低点日期 | E1: 07月前复权最低日内价 | F1: 数据状态 | G1: 来源 | H1: 复权序列 | I1: 6/7记录数 | J1: 7月记录数 | K1: 未覆盖交易日
A2: 002428 | B2: 2026-06-25 | C2: 132.87 | D2: 2026-07-21 | E2: 60.8 | F2: 正常 | G2: 腾讯财经 fqkline qfq（前复权）；https://web.ifzq.gtimg.cn/appstock/app/fqkline/get；读取日期 2026-08-09 | H2: qfqday | I2: 44 | J2: 23
A3: 688549 | B3: 2026-07-02 | C3: 44 | D3: 2026-07-21 | E3: 18.5 | F3: 正常 | G3: 腾讯财经 fqkline qfq（前复权）；https://web.ifzq.gtimg.cn/appstock/app/fqkline/get；读取日期 2026-08-09 | H3: qfqday | I3: 44 | J3: 23
A4: 300476 | B4: 2026-06-01 | C4: 381.68 | D4: 2026-07-30 | E4: 177.88 | F4: 正常 | G4: 腾讯财经 fqkline qfq（前复权）；https://web.ifzq.gtimg.cn/appstock/app/fqkline/get；读取日期 2026-08-09 | H4: qfqday | I4: 44 | J4: 23
A5: 688313 | B5: 2026-06-24 | C5: 206.67 | D5: 2026-07-30 | E5: 81.68 | F5: 正常 | G5: 腾讯财经 fqkline qfq（前复权）；https://web.ifzq.gtimg.cn/appstock/app/fqkline/get；读取日期 2026-08-09 | H5: qfqday | I5: 44 | J5: 23
A6: 688020 | B6: 2026-07-01 | C6: 290 | D6: 2026-07-30 | E6: 93 | F6: 正常 | G6: 腾讯财经 fqkline qfq（前复权）；https://web.ifzq.gtimg.cn/appstock/app/fqkline/get；读取日期 2026-08-09 | H6: qfqday | I6: 44 | J6: 23
A7: 688300 | B7: 2026-06-22 | C7: 297.31 | D7: 2026-07-30 | E7: 103.33 | F7: 正常 | G7: 腾讯财经 fqkline qfq（前复权）；https://web.ifzq.gtimg.cn/appstock/app/fqkline/get；读取日期 2026-08-09 | H7: qfqday | I7: 44 | J7: 23
A8: 300620 | B8: 2026-06-24 | C8: 413.3 | D8: 2026-07-21 | E8: 184.35 | F8: 正常 | G8: 腾讯财经 fqkline qfq（前复权）；https://web.ifzq.gtimg.cn/appstock/app/fqkline/get；读取日期 2026-08-09 | H8: qfqday | I8: 44 | J8: 23
A9: 301217 | B9: 2026-06-18 | C9: 202.15 | D9: 2026-07-30 | E9: 77.28 | F9: 正常 | G9: 腾讯财经 fqkline qfq（前复权）；https://web.ifzq.gtimg.cn/appstock/app/fqkline/get；读取日期 2026-08-09 | H9: qfqday | I9: 44 | J9: 23
A10: 688603 | B10: 2026-06-17 | C10: 213.74 | D10: 2026-07-30 | E10: 79.88 | F10: 正常 | G10: 腾讯财经 fqkline qfq（前复权）；https://web.ifzq.gtimg.cn/appstock/app/fqkline/get；读取日期 2026-08-09 | H10: qfqday | I10: 44 | J10: 23
A11: 688195 | B11: 2026-06-05 | C11: 252 | D11: 2026-07-21 | E11: 98.68 | F11: 正常 | G11: 腾讯财经 fqkline qfq（前复权）；https://web.ifzq.gtimg.cn/appstock/app/fqkline/get；读取日期 2026-08-09 | H11: qfqday | I11: 44 | J11: 23
A12: 688519 | B12: 2026-06-26 | C12: 439.82 | D12: 2026-07-30 | E12: 192 | F12: 正常 | G12: 腾讯财经 fqkline qfq（前复权）；https://web.ifzq.gtimg.cn/appstock/app/fqkline/get；读取日期 2026-08-09 | H12: qfqday | I12: 44 | J12: 23
A13: 600330 | B13: 2026-06-26 | C13: 37.37 | D13: 2026-07-21 | E13: 15.68 | F13: 正常 | G13: 腾讯财经 fqkline qfq（前复权）；https://web.ifzq.gtimg.cn/appstock/app/fqkline/get；读取日期 2026-08-09 | H13: qfqday | I13: 44 | J13: 23
... A38: 600110 | B38: 2026-06-18 | C38: 18.42 | D38: 2026-07-30 | E38: 7.89 | F38: 正常 | G38: 腾讯财经 fqkline qfq（前复权）；https://web.ifzq.gtimg.cn/appstock/app/fqkline/get；读取日期 2026-08-09 | H38: qfqday | I38: 44 | J38: 23
A39: 688031 | B39: 2026-06-04 | C39: 152.32 | D39: 2026-07-21 | E39: 78.18 | F39: 前复权同原始日线 | G39: 腾讯财经 fqkline qfq（前复权）；https://web.ifzq.gtimg.cn/appstock/app/fqkline/get；读取日期 2026-08-09 | H39: day（接口 qfq 请求未单列 qfqday） | I39: 44 | J39: 23 | K39: 接口 qfq 请求未单列 qfqday；返回日线用于无独立复权序列的代码
A40: 300576 | B40: 2026-06-29 | C40: 55.83 | D40: 2026-07-30 | E40: 23.91 | F40: 正常 | G40: 腾讯财经 fqkline qfq（前复权）；https://web.ifzq.gtimg.cn/appstock/app/fqkline/get；读取日期 2026-08-09 | H40: qfqday | I40: 44 | J40: 23
A41: 301205 | B41: 2026-06-22 | C41: 377.8 | D41: 2026-07-21 | E41: 153 | F41: 正常 | G41: 腾讯财经 fqkline qfq（前复权）；https://web.ifzq.gtimg.cn/appstock/app/fqkline/get；读取日期 2026-08-09 | H41: qfqday | I41: 44 | J41: 23
A42: 301128 | B42: 2026-06-16 | C42: 191.8 | D42: 2026-07-30 | E42: 84 | F42: 正常 | G42: 腾讯财经 fqkline qfq（前复权）；https://web.ifzq.gtimg.cn/appstock/app/fqkline/get；读取日期 2026-08-09 | H42: qfqday | I42: 44 | J42: 23
A43: 002222 | B43: 2026-06-22 | C43: 108.05 | D43: 2026-07-30 | E43: 47.3 | F43: 正常 | G43: 腾讯财经 fqkline qfq（前复权）；https://web.ifzq.gtimg.cn/appstock/app/fqkline/get；读取日期 2026-08-09 | H43: qfqday | I43: 44 | J43: 23
A44: 688678 | B44: 2026-06-30 | C44: 24.54 | D44: 2026-07-30 | E44: 13.7 | F44: 正常 | G44: 腾讯财经 fqkline qfq（前复权）；https://web.ifzq.gtimg.cn/appstock/app/fqkline/get；读取日期 2026-08-09 | H44: qfqday | I44: 44 | J44: 23
A45: 002741 | B45: 2026-06-22 | C45: 42.15 | D45: 2026-07-30 | E45: 19.81 | F45: 正常 | G45: 腾讯财经 fqkline qfq（前复权）；https://web.ifzq.gtimg.cn/appstock/app/fqkline/get；读取日期 2026-08-09 | H45: qfqday | I45: 44 | J45: 23
A46: 300548 | B46: 2026-06-22 | C46: 309.69 | D46: 2026-07-30 | E46: 123.48 | F46: 正常 | G46: 腾讯财经 fqkline qfq（前复权）；https://web.ifzq.gtimg.cn/appstock/app/fqkline/get；读取日期 2026-08-09 | H46: qfqday | I46: 44 | J46: 23
A47: 688167 | B47: 2026-06-16 | C47: 424.88 | D47: 2026-07-30 | E47: 155.5 | F47: 正常 | G47: 腾讯财经 fqkline qfq（前复权）；https://web.ifzq.gtimg.cn/appstock/app/fqkline/get；读取日期 2026-08-09 | H47: qfqday | I47: 44 | J47: 23
A48: 300570 | B48: 2026-06-22 | C48: 284.85 | D48: 2026-07-30 | E48: 102.3 | F48: 正常 | G48: 腾讯财经 fqkline qfq（前复权）；https://web.ifzq.gtimg.cn/appstock/app/fqkline/get；读取日期 2026-08-09 | H48: qfqday | I48: 44 | J48: 23
A49: 688183 | B49: 2026-06-17 | C49: 153.94 | D49: 2026-07-30 | E49: 81.5 | F49: 正常 | G49: 腾讯财经 fqkline qfq（前复权）；https://web.ifzq.gtimg.cn/appstock/app/fqkline/get；读取日期 2026-08-09 | H49: qfqday | I49: 44 | J49: 23
A50: 688048 | B50: 2026-07-01 | C50: 509.11 | D50: 2026-07-30 | E50: 206 | F50: 正常 | G50: 腾讯财经 fqkline qfq（前复权）；https://web.ifzq.gtimg.cn/appstock/app/fqkline/get；读取日期 2026-08-09 | H50: qfqday | I50: 44 | J50: 23
A51: 600487 | B51: 2026-06-23 | C51: 124.888 | D51: 2026-07-30 | E51: 45.6 | F51: 正常 | G51: 腾讯财经 fqkline qfq（前复权）；https://web.ifzq.gtimg.cn/appstock/app/fqkline/get；读取日期 2026-08-09 | H51: qfqday | I51: 44 | J51: 23
... A94: 300346 | B94: 2026-07-01 | C94: 98.82 | D94: 2026-07-21 | E94: 46.55 | F94: 正常 | G94: 腾讯财经 fqkline qfq（前复权）；https://web.ifzq.gtimg.cn/appstock/app/fqkline/get；读取日期 2026-08-09 | H94: qfqday | I94: 44 | J94: 23
A95: 688141 | B95: 2026-07-08 | C95: 185 | D95: 2026-07-30 | E95: 97.04 | F95: 前复权同原始日线 | G95: 腾讯财经 fqkline qfq（前复权）；https://web.ifzq.gtimg.cn/appstock/app/fqkline/get；读取日期 2026-08-09 | H95: day（接口 qfq 请求未单列 qfqday） | I95: 44 | J95: 23 | K95: 接口 qfq 请求未单列 qfqday；返回日线用于无独立复权序列的代码
A96: 688507 | B96: 2026-06-29 | C96: 306.85 | D96: 2026-07-30 | E96: 127.48 | F96: 正常 | G96: 腾讯财经 fqkline qfq（前复权）；https://web.ifzq.gtimg.cn/appstock/app/fqkline/get；读取日期 2026-08-09 | H96: qfqday | I96: 44 | J96: 23
A97: 300870 | B97: 2026-06-23 | C97: 403 | D97: 2026-07-30 | E97: 161.89 | F97: 正常 | G97: 腾讯财经 fqkline qfq（前复权）；https://web.ifzq.gtimg.cn/appstock/app/fqkline/get；读取日期 2026-08-09 | H97: qfqday | I97: 44 | J97: 23
A98: 600641 | B98: 2026-07-03 | C98: 50.99 | D98: 2026-07-30 | E98: 24.8 | F98: 正常 | G98: 腾讯财经 fqkline qfq（前复权）；https://web.ifzq.gtimg.cn/appstock/app/fqkline/get；读取日期 2026-08-09 | H98: qfqday | I98: 44 | J98: 23
A99: 601138 | B99: 2026-06-03 | C99: 84.3 | D99: 2026-07-30 | E99: 52.57 | F99: 正常 | G99: 腾讯财经 fqkline qfq（前复权）；https://web.ifzq.gtimg.cn/appstock/app/fqkline/get；读取日期 2026-08-09 | H99: qfqday | I99: 44 | J99: 23
A100: 603061 | B100: 2026-07-01 | C100: 550 | D100: 2026-07-30 | E100: 243.08 | F100: 正常 | G100: 腾讯财经 fqkline qfq（前复权）；https://web.ifzq.gtimg.cn/appstock/app/fqkline/get；读取日期 2026-08-09 | H100: qfqday | I100: 44 | J100: 23
A101: 688531 | B101: 2026-06-05 | C101: 214.404 | D101: 2026-07-30 | E101: 101.5 | F101: 正常 | G101: 腾讯财经 fqkline qfq（前复权）；https://web.ifzq.gtimg.cn/appstock/app/fqkline/get；读取日期 2026-08-09 | H101: qfqday | I101: 44 | J101: 23
A102: 688800 | B102: 2026-06-22 | C102: 105.46 | D102: 2026-07-30 | E102: 46.9 | F102: 正常 | G102: 腾讯财经 fqkline qfq（前复权）；https://web.ifzq.gtimg.cn/appstock/app/fqkline/get；读取日期 2026-08-09 | H102: qfqday | I102: 44 | J102: 23
A103: 603203 | B103: 2026-06-30 | C103: 82.96 | D103: 2026-07-30 | E103: 34.8 | F103: 正常 | G103: 腾讯财经 fqkline qfq（前复权）；https://web.ifzq.gtimg.cn/appstock/app/fqkline/get；读取日期 2026-08-09 | H103: qfqday | I103: 44 | J103: 23
A104: 603989 | B104: 2026-06-26 | C104: 57.8 | D104: 2026-07-30 | E104: 23.47 | F104: 正常 | G104: 腾讯财经 fqkline qfq（前复权）；https://web.ifzq.gtimg.cn/appstock/app/fqkline/get；读取日期 2026-08-09 | H104: qfqday | I104: 44 | J104: 23
A105: 301526 | B105: 2026-06-26 | C105: 54.08 | D105: 2026-07-21 | E105: 24.05 | F105: 正常 | G105: 腾讯财经 fqkline qfq（前复权）；https://web.ifzq.gtimg.cn/appstock/app/fqkline/get；读取日期 2026-08-09 | H105: qfqday | I105: 44 | J105: 23
A106: 603297 | B106: 2026-06-30 | C106: 146.98 | D106: 2026-07-30 | E106: 86.4 | F106: 正常 | G106: 腾讯财经 fqkline qfq（前复权）；https://web.ifzq.gtimg.cn/appstock/app/fqkline/get；读取日期 2026-08-09 | H106: qfqday | I106: 44 | J106: 23
A107: 688521 | B107: 2026-06-30 | C107: 375.67 | D107: 2026-07-30 | E107: 170.21 | F107: 前复权同原始日线 | G107: 腾讯财经 fqkline qfq（前复权）；https://web.ifzq.gtimg.cn/appstock/app/fqkline/get；读取日期 2026-08-09 | H107: day（接口 qfq 请求未单列 qfqday） | I107: 44 | J107: 23 | K107: 接口 qfq 请求未单列 qfqday；返回日线用于无独立复权序列的代码
A108: 002281 | B108: 2026-06-22 | C108: 279 | D108: 2026-07-30 | E108: 152.33 | F108: 正常 | G108: 腾讯财经 fqkline qfq（前复权）；https://web.ifzq.gtimg.cn/appstock/app/fqkline/get；读取日期 2026-08-09 | H108: qfqday | I108: 44 | J108: 23
A109: 300684 | B109: 2026-07-10 | C109: 74.63 | D109: 2026-07-30 | E109: 41.45 | F109: 正常 | G109: 腾讯财经 fqkline qfq（前复权）；https://web.ifzq.gtimg.cn/appstock/app/fqkline/get；读取日期 2026-08-09 | H109: qfqday | I109: 44 | J109: 23
A110: 301611 | B110: 2026-07-01 | C110: 191.56 | D110: 2026-07-30 | E110: 78.02 | F110: 正常 | G110: 腾讯财经 fqkline qfq（前复权）；https://web.ifzq.gtimg.cn/appstock/app/fqkline/get；读取日期 2026-08-09 | H110: qfqday | I110: 44 | J110: 23
A111: 688322 | B111: 2026-07-03 | C111: 153.3 | D111: 2026-07-30 | E111: 79.21 | F111: 前复权同原始日线 | G111: 腾讯财经 fqkline qfq（前复权）；https://web.ifzq.gtimg.cn/appstock/app/fqkline/get；读取日期 2026-08-09 | H111: day（接口 qfq 请求未单列 qfqday） | I111: 44 | J111: 23 | K111: 接口 qfq 请求未单列 qfqday；返回日线用于无独立复权序列的代码
A112: 603650 | B112: 2026-07-01 | C112: 102.28 | D112: 2026-07-30 | E112: 53.44 | F112: 正常 | G112: 腾讯财经 fqkline qfq（前复权）；https://web.ifzq.gtimg.cn/appstock/app/fqkline/get；读取日期 2026-08-09 | H112: qfqday | I112: 44 | J112: 23
A113: 688001 | B113: 2026-06-26 | C113: 94.018 | D113: 2026-07-30 | E113: 41.24 | F113: 正常 | G113: 腾讯财经 fqkline qfq（前复权）；https://web.ifzq.gtimg.cn/appstock/app/fqkline/get；读取日期 2026-08-09 | H113: qfqday | I113: 44 | J113: 23
A114: 603083 | B114: 2026-06-25 | C114: 263.3 | D114: 2026-07-31 | E114: 130.08 | F114: 正常 | G114: 腾讯财经 fqkline qfq（前复权）；https://web.ifzq.gtimg.cn/appstock/app/fqkline/get；读取日期 2026-08-09 | H114: qfqday | I114: 44 | J114: 23
A115: 688035 | B115: 2026-06-22 | C115: 107.28 | D115: 2026-07-30 | E115: 52 | F115: 正常 | G115: 腾讯财经 fqkline qfq（前复权）；https://web.ifzq.gtimg.cn/appstock/app/fqkline/get；读取日期 2026-08-09 | H115: qfqday | I115: 44 | J115: 23
A116: 688146 | B116: 2026-06-26 | C116: 416.99 | D116: 2026-07-21 | E116: 161.37 | F116: 正常；按已记录交易日统计 | G116: 腾讯财经 fqkline qfq（前复权）；https://web.ifzq.gtimg.cn/appstock/app/fqkline/get；读取日期 2026-08-09 | H116: qfqday | I116: 41 | J116: 23 | K116: 2026-06-23、2026-06-24、2026-06-25
A117: 688362 | B117: 2026-07-10 | C117: 120.8 | D117: 2026-07-30 | E117: 55.55 | F117: 正常 | G117: 腾讯财经 fqkline qfq（前复权）；https://web.ifzq.gtimg.cn/appstock/app/fqkline/get；读取日期 2026-08-09 | H117: qfqday | I117: 44 | J117: 23
A118: 688135 | B118: 2026-07-10 | C118: 48.56 | D118: 2026-07-30 | E118: 19.75 | F118: 正常 | G118: 腾讯财经 fqkline qfq（前复权）；https://web.ifzq.gtimg.cn/appstock/app/fqkline/get；读取日期 2026-08-09 | H118: qfqday | I118: 44 | J118: 23
A119: 688409 | B119: 2026-07-01 | C119: 333.33 | D119: 2026-07-21 | E119: 151 | F119: 正常 | G119: 腾讯财经 fqkline qfq（前复权）；https://web.ifzq.gtimg.cn/appstock/app/fqkline/get；读取日期 2026-08-09 | H119: qfqday | I119: 44 | J119: 23
A120: 600584 | B120: 2026-07-10 | C120: 113.87 | D120: 2026-07-30 | E120: 64.51 | F120: 正常 | G120: 腾讯财经 fqkline qfq（前复权）；https://web.ifzq.gtimg.cn/appstock/app/fqkline/get；读取日期 2026-08-09 | H120: qfqday | I120: 44 | J120: 23
A121: 688234 | B121: 2026-06-25 | C121: 188.88 | D121: 2026-07-30 | E121: 81.21 | F121: 前复权同原始日线 | G121: 腾讯财经 fqkline qfq（前复权）；https://web.ifzq.gtimg.cn/appstock/app/fqkline/get；读取日期 2026-08-09 | H121: day（接口 qfq 请求未单列 qfqday） | I121: 44 | J121: 23 | K121: 接口 qfq 请求未单列 qfqday；返回日线用于无独立复权序列的代码
A122: 000636 | B122: 2026-06-29 | C122: 83.901 | D122: 2026-07-21 | E122: 37.69 | F122: 正常 | G122: 腾讯财经 fqkline qfq（前复权）；https://web.ifzq.gtimg.cn/appstock/app/fqkline/get；读取日期 2026-08-09 | H122: qfqday | I122: 44 | J122: 23
A123: 300323 | B123: 2026-07-02 | C123: 22.7 | D123: 2026-07-30 | E123: 9.95 | F123: 正常 | G123: 腾讯财经 fqkline qfq（前复权）；https://web.ifzq.gtimg.cn/appstock/app/fqkline/get；读取日期 2026-08-09 | H123: qfqday | I123: 44 | J123: 23
A124: 600522 | B124: 2026-06-25 | C124: 67.84 | D124: 2026-07-30 | E124: 27.02 | F124: 正常 | G124: 腾讯财经 fqkline qfq（前复权）；https://web.ifzq.gtimg.cn/appstock/app/fqkline/get；读取日期 2026-08-09 | H124: qfqday | I124: 44 | J124: 23
A125: 002008 | B125: 2026-06-26 | C125: 168.08 | D125: 2026-07-30 | E125: 81.9 | F125: 正常 | G125: 腾讯财经 fqkline qfq（前复权）；https://web.ifzq.gtimg.cn/appstock/app/fqkline/get；读取日期 2026-08-09 | H125: qfqday | I125: 44 | J125: 23
A126: 301328 | B126: 2026-07-03 | C126: 85.98 | D126: 2026-07-30 | E126: 43.3 | F126: 正常 | G126: 腾讯财经 fqkline qfq（前复权）；https://web.ifzq.gtimg.cn/appstock/app/fqkline/get；读取日期 2026-08-09 | H126: qfqday | I126: 44 | J126: 23
A127: 002119 | B127: 2026-07-02 | C127: 41.8 | D127: 2026-07-30 | E127: 19.07 | F127: 正常 | G127: 腾讯财经 fqkline qfq（前复权）；https://web.ifzq.gtimg.cn/appstock/app/fqkline/get；读取日期 2026-08-09 | H127: qfqday | I127: 44 | J127: 23
A128: 002837 | B128: 2026-06-25 | C128: 89.69 | D128: 2026-07-30 | E128: 47.15 | F128: 正常 | G128: 腾讯财经 fqkline qfq（前复权）；https://web.ifzq.gtimg.cn/appstock/app/fqkline/get；读取日期 2026-08-09 | H128: qfqday | I128: 44 | J128: 23
A129: 603688 | B129: 2026-06-29 | C129: 89.5 | D129: 2026-07-30 | E129: 40.22 | F129: 正常 | G129: 腾讯财经 fqkline qfq（前复权）；https://web.ifzq.gtimg.cn/appstock/app/fqkline/get；读取日期 2026-08-09 | H129: qfqday | I129: 44 | J129: 23
A130: 600703 | B130: 2026-06-26 | C130: 23.18 | D130: 2026-07-21 | E130: 10.84 | F130: 正常 | G130: 腾讯财经 fqkline qfq（前复权）；https://web.ifzq.gtimg.cn/appstock/app/fqkline/get；读取日期 2026-08-09 | H130: qfqday | I130: 44 | J130: 23
A131: 301413 | B131: 2026-06-05 | C131: 95 | D131: 2026-07-21 | E131: 50.71 | F131: 正常 | G131: 腾讯财经 fqkline qfq（前复权）；https://web.ifzq.gtimg.cn/appstock/app/fqkline/get；读取日期 2026-08-09 | H131: qfqday | I131: 44 | J131: 23
A132: 300602 | B132: 2026-06-26 | C132: 52.92 | D132: 2026-07-30 | E132: 30.66 | F132: 正常 | G132: 腾讯财经 fqkline qfq（前复权）；https://web.ifzq.gtimg.cn/appstock/app/fqkline/get；读取日期 2026-08-09 | H132: qfqday | I132: 44 | J132: 23
A133: 300537 | B133: 2026-07-01 | C133: 36.45 | D133: 2026-07-21 | E133: 15.5 | F133: 正常 | G133: 腾讯财经 fqkline qfq（前复权）；https://web.ifzq.gtimg.cn/appstock/app/fqkline/get；读取日期 2026-08-09 | H133: qfqday | I133: 44 | J133: 23
A134: 300857 | B134: 2026-06-25 | C134: 355.55 | D134: 2026-07-30 | E134: 183.61 | F134: 正常 | G134: 腾讯财经 fqkline qfq（前复权）；https://web.ifzq.gtimg.cn/appstock/app/fqkline/get；读取日期 2026-08-09 | H134: qfqday | I134: 44 | J134: 23
A135: 688702 | B135: 2026-07-22 | C135: 458.88 | D135: 2026-07-30 | E135: 297.1 | F135: 前复权同原始日线 | G135: 腾讯财经 fqkline qfq（前复权）；https://web.ifzq.gtimg.cn/appstock/app/fqkline/get；读取日期 2026-08-09 | H135: day（接口 qfq 请求未单列 qfqday） | I135: 44 | J135: 23 | K135: 接口 qfq 请求未单列 qfqday；返回日线用于无独立复权序列的代码
A136: 688286 | B136: 2026-07-01 | C136: 98.641 | D136: 2026-07-30 | E136: 36.5 | F136: 正常 | G136: 腾讯财经 fqkline qfq（前复权）；https://web.ifzq.gtimg.cn/appstock/app/fqkline/get；读取日期 2026-08-09 | H136: qfqday | I136: 44 | J136: 23
A137: 603324 | B137: 2026-07-01 | C137: 56.39 | D137: 2026-07-30 | E137: 22.9 | F137: 正常 | G137: 腾讯财经 fqkline qfq（前复权）；https://web.ifzq.gtimg.cn/appstock/app/fqkline/get；读取日期 2026-08-09 | H137: qfqday | I137: 44 | J137: 23
A138: 600176 | B138: 2026-06-26 | C138: 77.2 | D138: 2026-07-30 | E138: 35.55 | F138: 正常 | G138: 腾讯财经 fqkline qfq（前复权）；https://web.ifzq.gtimg.cn/appstock/app/fqkline/get；读取日期 2026-08-09 | H138: qfqday | I138: 44 | J138: 23
A139: 300567 | B139: 2026-07-01 | C139: 335.12 | D139: 2026-07-30 | E139: 175.58 | F139: 正常；按已记录交易日统计 | G139: 腾讯财经 fqkline qfq（前复权）；https://web.ifzq.gtimg.cn/appstock/app/fqkline/get；读取日期 2026-08-09 | H139: qfqday | I139: 39 | J139: 18 | K139: 2026-07-09、2026-07-10、2026-07-13、2026-07-14、2026-07-15
A140: 605111 | B140: 2026-07-01 | C140: 104.43 | D140: 2026-07-21 | E140: 45.14 | F140: 正常 | G140: 腾讯财经 fqkline qfq（前复权）；https://web.ifzq.gtimg.cn/appstock/app/fqkline/get；读取日期 2026-08-09 | H140: qfqday | I140: 44 | J140: 23
A141: 688368 | B141: 2026-06-25 | C141: 231.2 | D141: 2026-07-30 | E141: 100 | F141: 正常 | G141: 腾讯财经 fqkline qfq（前复权）；https://web.ifzq.gtimg.cn/appstock/app/fqkline/get；读取日期 2026-08-09 | H141: qfqday | I141: 44 | J141: 23
A142: 688106 | B142: 2026-07-02 | C142: 51.91 | D142: 2026-07-30 | E142: 25.58 | F142: 正常 | G142: 腾讯财经 fqkline qfq（前复权）；https://web.ifzq.gtimg.cn/appstock/app/fqkline/get；读取日期 2026-08-09 | H142: qfqday | I142: 44 | J142: 23
A143: 300398 | B143: 2026-06-29 | C143: 65.235 | D143: 2026-07-21 | E143: 28.56 | F143: 正常 | G143: 腾讯财经 fqkline qfq（前复权）；https://web.ifzq.gtimg.cn/appstock/app/fqkline/get；读取日期 2026-08-09 | H143: qfqday | I143: 44 | J143: 23
A144: 002859 | B144: 2026-07-01 | C144: 115.91 | D144: 2026-07-21 | E144: 51.4 | F144: 正常 | G144: 腾讯财经 fqkline qfq（前复权）；https://web.ifzq.gtimg.cn/appstock/app/fqkline/get；读取日期 2026-08-09 | H144: qfqday | I144: 44 | J144: 23
A145: 002851 | B145: 2026-06-23 | C145: 189.95 | D145: 2026-07-30 | E145: 96.77 | F145: 正常 | G145: 腾讯财经 fqkline qfq（前复权）；https://web.ifzq.gtimg.cn/appstock/app/fqkline/get；读取日期 2026-08-09 | H145: qfqday | I145: 44 | J145: 23
A146: 002903 | B146: 2026-06-18 | C146: 54.9 | D146: 2026-07-21 | E146: 20.05 | F146: 正常 | G146: 腾讯财经 fqkline qfq（前复权）；https://web.ifzq.gtimg.cn/appstock/app/fqkline/get；读取日期 2026-08-09 | H146: qfqday | I146: 44 | J146: 23
A147: 300661 | B147: 2026-07-02 | C147: 151.9 | D147: 2026-07-30 | E147: 88.72 | F147: 正常 | G147: 腾讯财经 fqkline qfq（前复权）；https://web.ifzq.gtimg.cn/appstock/app/fqkline/get；读取日期 2026-08-09 | H147: qfqday | I147: 44 | J147: 23
A148: 688652 | B148: 2026-07-01 | C148: 240.075 | D148: 2026-07-30 | E148: 122.67 | F148: 正常 | G148: 腾讯财经 fqkline qfq（前复权）；https://web.ifzq.gtimg.cn/appstock/app/fqkline/get；读取日期 2026-08-09 | H148: qfqday | I148: 44 | J148: 23
A149: 688401 | B149: 2026-07-01 | C149: 103.9 | D149: 2026-07-21 | E149: 56.2 | F149: 正常 | G149: 腾讯财经 fqkline qfq（前复权）；https://web.ifzq.gtimg.cn/appstock/app/fqkline/get；读取日期 2026-08-09 | H149: qfqday | I149: 44 | J149: 23
A150: 688628 | B150: 2026-06-22 | C150: 119.2 | D150: 2026-07-21 | E150: 53.28 | F150: 正常 | G150: 腾讯财经 fqkline qfq（前复权）；https://web.ifzq.gtimg.cn/appstock/app/fqkline/get；读取日期 2026-08-09 | H150: qfqday | I150: 44 | J150: 23
A151: 002138 | B151: 2026-07-01 | C151: 79.72 | D151: 2026-07-21 | E151: 36.71 | F151: 正常 | G151: 腾讯财经 fqkline qfq（前复权）；https://web.ifzq.gtimg.cn/appstock/app/fqkline/get；读取日期 2026-08-09 | H151: qfqday | I151: 44 | J151: 23
... A174: 688337 | B174: 2026-06-22 | C174: 81.8 | D174: 2026-07-21 | E174: 35.31 | F174: 正常 | G174: 腾讯财经 fqkline qfq（前复权）；https://web.ifzq.gtimg.cn/appstock/app/fqkline/get；读取日期 2026-08-09 | H174: qfqday | I174: 44 | J174: 23
A175: 688515 | B175: 2026-06-22 | C175: 274 | D175: 2026-07-21 | E175: 115.78 | F175: 前复权同原始日线 | G175: 腾讯财经 fqkline qfq（前复权）；https://web.ifzq.gtimg.cn/appstock/app/fqkline/get；读取日期 2026-08-09 | H175: day（接口 qfq 请求未单列 qfqday） | I175: 44 | J175: 23 | K175: 接口 qfq 请求未单列 qfqday；返回日线用于无独立复权序列的代码
A176: 688123 | B176: 2026-07-10 | C176: 235.99 | D176: 2026-07-21 | E176: 105.4 | F176: 正常 | G176: 腾讯财经 fqkline qfq（前复权）；https://web.ifzq.gtimg.cn/appstock/app/fqkline/get；读取日期 2026-08-09 | H176: qfqday | I176: 44 | J176: 23
A177: 300302 | B177: 2026-06-25 | C177: 62 | D177: 2026-07-21 | E177: 24.5 | F177: 正常 | G177: 腾讯财经 fqkline qfq（前复权）；https://web.ifzq.gtimg.cn/appstock/app/fqkline/get；读取日期 2026-08-09 | H177: qfqday | I177: 44 | J177: 23
A178: 300285 | B178: 2026-06-29 | C178: 112.88 | D178: 2026-07-20 | E178: 47.77 | F178: 正常 | G178: 腾讯财经 fqkline qfq（前复权）；https://web.ifzq.gtimg.cn/appstock/app/fqkline/get；读取日期 2026-08-09 | H178: qfqday | I178: 44 | J178: 23
A179: 300657 | B179: 2026-06-18 | C179: 51 | D179: 2026-07-30 | E179: 29.38 | F179: 正常 | G179: 腾讯财经 fqkline qfq（前复权）；https://web.ifzq.gtimg.cn/appstock/app/fqkline/get；读取日期 2026-08-09 | H179: qfqday | I179: 44 | J179: 23
A180: 688200 | B180: 2026-07-01 | C180: 570 | D180: 2026-07-21 | E180: 328.15 | F180: 正常 | G180: 腾讯财经 fqkline qfq（前复权）；https://web.ifzq.gtimg.cn/appstock/app/fqkline/get；读取日期 2026-08-09 | H180: qfqday | I180: 44 | J180: 23
A181: 688691 | B181: 2026-07-10 | C181: 120.7 | D181: 2026-07-30 | E181: 56.58 | F181: 正常 | G181: 腾讯财经 fqkline qfq（前复权）；https://web.ifzq.gtimg.cn/appstock/app/fqkline/get；读取日期 2026-08-09 | H181: qfqday | I181: 44 | J181: 23
A182: 002156 | B182: 2026-07-15 | C182: 84.7 | D182: 2026-07-30 | E182: 55.89 | F182: 正常 | G182: 腾讯财经 fqkline qfq（前复权）；https://web.ifzq.gtimg.cn/appstock/app/fqkline/get；读取日期 2026-08-09 | H182: qfqday | I182: 44 | J182: 23
A183: 300408 | B183: 2026-06-29 | C183: 180.35 | D183: 2026-07-21 | E183: 86.03 | F183: 正常 | G183: 腾讯财经 fqkline qfq（前复权）；https://web.ifzq.gtimg.cn/appstock/app/fqkline/get；读取日期 2026-08-09 | H183: qfqday | I183: 44 | J183: 23
A184: 002782 | B184: 2026-06-01 | C184: 28.32 | D184: 2026-07-21 | E184: 12.47 | F184: 正常 | G184: 腾讯财经 fqkline qfq（前复权）；https://web.ifzq.gtimg.cn/appstock/app/fqkline/get；读取日期 2026-08-09 | H184: qfqday | I184: 44 | J184: 23
A185: 002384 | B185: 2026-07-15 | C185: 280.08 | D185: 2026-07-30 | E185: 161.8 | F185: 正常 | G185: 腾讯财经 fqkline qfq（前复权）；https://web.ifzq.gtimg.cn/appstock/app/fqkline/get；读取日期 2026-08-09 | H185: qfqday | I185: 44 | J185: 23
A186: 688052 | B186: 2026-06-24 | C186: 307.29 | D186: 2026-07-30 | E186: 177.5 | F186: 正常 | G186: 腾讯财经 fqkline qfq（前复权）；https://web.ifzq.gtimg.cn/appstock/app/fqkline/get；读取日期 2026-08-09 | H186: qfqday | I186: 44 | J186: 23
A187: 688226 | B187: 2026-06-05 | C187: 50.27 | D187: 2026-07-21 | E187: 24.65 | F187: 正常 | G187: 腾讯财经 fqkline qfq（前复权）；https://web.ifzq.gtimg.cn/appstock/app/fqkline/get；读取日期 2026-08-09 | H187: qfqday | I187: 44 | J187: 23
... A257: 002171 | B257: 2026-06-22 | C257: 16.47 | D257: 2026-07-20 | E257: 8.59 | F257: 正常 | G257: 腾讯财经 fqkline qfq（前复权）；https://web.ifzq.gtimg.cn/appstock/app/fqkline/get；读取日期 2026-08-09 | H257: qfqday | I257: 44 | J257: 23
...
